cli_spectrogram/__init__.py
cli_spectrogram/cli_spectrogram.py
cli_spectrogram/common.py
cli_spectrogram/specgram.py
cli_spectrogram/ui.py
cli_spectrogram-1.0.0.dist-info/LICENSE
cli_spectrogram-1.0.0.dist-info/METADATA
cli_spectrogram-1.0.0.dist-info/WHEEL
cli_spectrogram-1.0.0.dist-info/entry_points.txt
cli_spectrogram-1.0.0.dist-info/top_level.txt
cli_spectrogram-1.0.0.dist-info/RECORD
