Metadata-Version: 2.1
Name: cli-spectrogram
Version: 1.0.0
Summary: Simple python module that creates spectrograms from multi channel hydrophone array data in the command line.
Home-page: https://github.com/caileighf/cli-spectrogram
Author: Caileigh Fitzgerald
Author-email: cfitzgerald@whoi.edu
License: UNKNOWN
Download-URL: https://github.com/caileighf/cli-spectrogram/archive/1.0.0.tar.gz
Platform: UNKNOWN
Classifier: Development Status :: 4 - Beta
Classifier: Environment :: Console :: Curses
Classifier: Topic :: Scientific/Engineering :: Visualization
Classifier: Topic :: Software Development :: User Interfaces
Classifier: Programming Language :: Python
Classifier: Operating System :: POSIX :: Linux
Requires-Python: >=2.7
Requires-Dist: numpy
Requires-Dist: pathlib
